pycaputo/__init__.py
pycaputo/benchmark.py
pycaputo/controller.py
pycaputo/derivatives.py
pycaputo/events.py
pycaputo/finite_difference.py
pycaputo/generating_functions.py
pycaputo/grid.py
pycaputo/history.py
pycaputo/implicit.py
pycaputo/interpolation.py
pycaputo/jacobi.py
pycaputo/lagrange.py
pycaputo/lipschitz.py
pycaputo/logging.py
pycaputo/py.typed
pycaputo/special.py
pycaputo/stepping.py
pycaputo/typing.py
pycaputo/utils.py
pycaputo/differentiation/__init__.py
pycaputo/differentiation/base.py
pycaputo/differentiation/caputo.py
pycaputo/differentiation/grunwald_letnikov.py
pycaputo/differentiation/riemann_liouville.py
pycaputo/fode/__init__.py
pycaputo/fode/caputo.py
pycaputo/fode/caputo_fabrizio.py
pycaputo/fode/gallery.py
pycaputo/fode/product_integration.py
pycaputo/fode/special.py
pycaputo/fode/variable_caputo.py
pycaputo/integrate_fire/__init__.py
pycaputo/integrate_fire/ad_ex.py
pycaputo/integrate_fire/base.py
pycaputo/integrate_fire/eif.py
pycaputo/integrate_fire/lif.py
pycaputo/integrate_fire/pif.py
pycaputo/integrate_fire/spikes.py
pycaputo/quadrature/__init__.py
pycaputo/quadrature/base.py
pycaputo/quadrature/riemann_liouville.py
pycaputo/quadrature/variable_riemann_liouville.py
pycaputo-0.10.1.dist-info/METADATA
pycaputo-0.10.1.dist-info/WHEEL
pycaputo-0.10.1.dist-info/RECORD
