Metadata-Version: 2.4
Name: pycaputo
Version: 0.10.1
Summary: Evaluate fractional integrals and solve fractional ODEs
Project-URL: Documentation, https://pycaputo.readthedocs.io
Project-URL: Repository, https://github.com/alexfikl/pycaputo
Author-email: Alexandru Fikl <alexfikl@gmail.com>
Maintainer-email: Alexandru Fikl <alexfikl@gmail.com>
License-Expression: MIT
Keywords: fractional-derivatives,fractional-integrals,quadrature,time-stepping
Classifier: Development Status :: 3 - Alpha
Classifier: Intended Audience :: Developers
Classifier: Intended Audience :: Other Audience
Classifier: Intended Audience :: Science/Research
Classifier: Natural Language :: English
Classifier: Programming Language :: Python
Classifier: Programming Language :: Python :: 3 :: Only
Classifier: Programming Language :: Python :: 3.10
Classifier: Programming Language :: Python :: 3.11
Classifier: Programming Language :: Python :: 3.12
Classifier: Programming Language :: Python :: 3.13
Classifier: Programming Language :: Python :: 3.14
Classifier: Topic :: Scientific/Engineering
Classifier: Topic :: Utilities
Requires-Python: >=3.10
Requires-Dist: array-api-compat>=1.11
Requires-Dist: numpy>=2.1
Requires-Dist: pymittagleffler>=0.1
Requires-Dist: rich>=13
Requires-Dist: scipy>=1.7
Requires-Dist: typing-extensions>=4
Provides-Extra: docs
Requires-Dist: sphinx-book-theme; extra == 'docs'
Requires-Dist: sphinx-design>=0.4; extra == 'docs'
Requires-Dist: sphinx>=6; extra == 'docs'
